curl2req/__init__.py
curl2req/curl.py
curl2req/parser.py
curl2req/path.py
curl2req/req.py
curl2req-0.1.8.dist-info/LICENSE
curl2req-0.1.8.dist-info/METADATA
curl2req-0.1.8.dist-info/WHEEL
curl2req-0.1.8.dist-info/top_level.txt
curl2req-0.1.8.dist-info/RECORD
