Metadata-Version: 2.2
Name: curl2req
Version: 0.1.8
Summary: bash curl transfer to requests
Home-page: https://github.com/azhao1981/curl2req
Author: weiz
Author-email: weiz <azhao.1981@gmail.com>
License: MIT License
Project-URL: Homepage, https://github.com/azhao1981/curl2req
Project-URL: Bug Tracker, https://github.com/azhao1981/curl2req/issues
Classifier: Programming Language :: Python :: 3
Classifier: License :: OSI Approved :: MIT License
Classifier: Operating System :: OS Independent
Requires-Python: >=3.7
License-File: LICENSE
Requires-Dist: requests
Requires-Dist: pydantic
Requires-Dist: curlparser
Requires-Dist: jsonpath_ng
Provides-Extra: dev
Requires-Dist: pytest; extra == "dev"
Requires-Dist: flake8; extra == "dev"
Requires-Dist: sphinx; extra == "dev"
Dynamic: author
Dynamic: home-page
